[
  {
    "title": "Spice Rack",
    "upgrade": "Ambrosia",
    "tier": "blue",
    "details": {
      "rules": {
        "cast": "Swap the flavours of two objects within your reach.",
        "hand": null
      },
      "flavour": "Mmm, Crayons.",
      "image": "res/art/illustration/Spice Rack.png"
    }
  },
  {
    "title": "Ambrosia",
    "upgrade": null,
    "tier": "green",
    "details": {
      "rules": {
        "cast": "Summon an irresistable brick of Ambrosia, food of the Gods.",
        "hand": null
      },
      "flavour": "Lifelong Ambrosia addicts scuttle around gourmet kitchens like rats, hoping to find tiny scraps.",
      "image": "res/art/illustration/Ambrosia.png"
    }
  }
]
