{"Foo":{"image_url":"https://raw.githubusercontent.com/elliottomlinson/rpcg/master/res/card/printed/Foo.png","spec":{"title":"Foo","rules":{"text":"Oh no"},"upgrade":"Bar","tier":"blue","flavour":"Darn","art_path":"res/card/art/illustration/Inner Sun.png","tags":["demo","hatred-series"]},"back_url":"https://raw.githubusercontent.com/elliottomlinson/rpcg/master/res/card/back/blue.png"},"Bar":{"image_url":"https://raw.githubusercontent.com/elliottomlinson/rpcg/master/res/card/printed/Bar.png","spec":{"title":"Bar","rules":{"text":"Sacrifice your life. Kill an NPC who you've met."},"upgrade":null,"tier":"green","flavour":"\"My hatred for you makes the sun rise. Without it, I am nothing.\" - Final Words of Fester the Limp","art_path":"res/card/art/illustration/Inner Sun.png","tags":["demo","hatred-series"]},"back_url":"https://raw.githubusercontent.com/elliottomlinson/rpcg/master/res/card/back/green.png"}}